Legacy/ARUSTUFF.py
Legacy/Corners.py
Legacy/LIDARFileSearch.py
Legacy/Legacy.py
Legacy/ModelsV2.py
Legacy/Plane.py
Legacy/VelLoader.py
Legacy/__init__.py
Legacy/py_util.py
porteratzolibs/__init__.py
porteratzolibs/Misc/CameraStuff.py
porteratzolibs/Misc/__init__.py
porteratzolibs/Misc/geometry.py
porteratzolibs/Misc/tictoc.py
porteratzolibs/Misc/transforms.py
porteratzolibs/ThreeDProcessing/ThreeDPreocessing.py
porteratzolibs/ThreeDProcessing/__init__.py
porteratzolibs/ThreeDProcessing/pclpy_utils.py
porteratzolibs/visualization_o3d/__init__.py
porteratzolibs/visualization_o3d/create_geometries.py
porteratzolibs/visualization_o3d/open3d_pointsetClass.py
porteratzolibs/visualization_o3d/open3d_utils.py
porteratzolibs/visualization_o3d/open3dvis.py
porteratzolibs-0.1.2.dist-info/LICENSE
porteratzolibs-0.1.2.dist-info/METADATA
porteratzolibs-0.1.2.dist-info/WHEEL
porteratzolibs-0.1.2.dist-info/top_level.txt
porteratzolibs-0.1.2.dist-info/RECORD
